{
  "0": [
    {
      "title": "Тестовая трансляция",
      "file": "https://archive.org/download/electricsheep-flock-248-30000-0/00248%3D30020%3D27231%3D25654.mp4",
      "duration": 600
    }
  ],
  "1": [
    {
      "title": "Тестовая трансляция",
      "file": "https://archive.org/download/electricsheep-flock-248-30000-0/00248%3D30020%3D27231%3D25654.mp4",
      "duration": 600
    }
  ],
  "2": [
    {
      "title": "Тестовая трансляция",
      "file": "https://archive.org/download/electricsheep-flock-248-30000-0/00248%3D30020%3D27231%3D25654.mp4",
      "duration": 600
    }
  ],
  "3": [
    {
      "title": "Тестовая трансляция",
      "file": "https://archive.org/download/electricsheep-flock-248-30000-0/00248%3D30020%3D27231%3D25654.mp4",
      "duration": 600
    }
  ],
  "4": [
    {
      "title": "Тестовая трансляция",
      "file": "https://archive.org/download/electricsheep-flock-248-30000-0/00248%3D30020%3D27231%3D25654.mp4",
      "duration": 600
    }
  ],
  "5": [
    {
      "title": "Тестовая трансляция",
      "file": "https://archive.org/download/electricsheep-flock-248-30000-0/00248%3D30020%3D27231%3D25654.mp4",
      "duration": 600
    }
  ],
  "6": [
    {
      "title": "Тестовая трансляция",
      "file": "https://archive.org/download/electricsheep-flock-248-30000-0/00248%3D30020%3D27231%3D25654.mp4",
      "duration": 600
    }
  ]
}
